signalboxclient/__init__.py
signalboxclient/client.py
signalboxclient/client_functions.py
signalboxclient/exceptions.py
signalboxclient/experiments.py
signalboxclient/features.py
signalboxclient/items_recommenders.py
signalboxclient/pagination.py
signalboxclient/parameter_recommenders.py
signalboxclient/parameters.py
signalboxclient/product_recommenders.py
signalboxclient/products.py
signalboxclient/target_variables.py
signalboxclient/touchpoints.py
signalboxclient/trackedusers.py
signalboxclient-0.1.21.dist-info/LICENSE
signalboxclient-0.1.21.dist-info/WHEEL
signalboxclient-0.1.21.dist-info/METADATA
signalboxclient-0.1.21.dist-info/RECORD
