Metadata-Version: 2.1
Name: signalboxclient
Version: 0.1.21
Summary: A library used as a Four2/SignalBox client.
Home-page: https://www.four2.ai
Author: Rian Finnegan
Author-email: rian@four2.ai
Classifier: License :: OSI Approved :: MIT License
